orgbabelhelper/__init__.py
orgbabelhelper/orgbabelhelper.py
orgbabelhelper-1.0.3.dist-info/DESCRIPTION.rst
orgbabelhelper-1.0.3.dist-info/METADATA
orgbabelhelper-1.0.3.dist-info/RECORD
orgbabelhelper-1.0.3.dist-info/WHEEL
orgbabelhelper-1.0.3.dist-info/metadata.json
orgbabelhelper-1.0.3.dist-info/top_level.txt
