Metadata-Version: 2.0
Name: orgbabelhelper
Version: 1.0.3
Summary: python helper module for Emacs org mode babel
Home-page: https://github.com/dfeich/org-babel-examples/tree/master/python
Author: Derek Feichtinger
Author-email: dfeich@gmail.com
License: GPL
Platform: UNKNOWN
Classifier: Development Status :: 4 - Beta
Classifier: Intended Audience :: Developers
Classifier: Programming Language :: Python :: 3
Requires-Dist: pandas
